Metadata-Version: 2.1
Name: ryw-textcompared
Version: 0.0.4
Summary: good job.
Author: yiwei.ru
Author-email: ruyiwei.cas@gmail.com
Classifier: Development Status :: 3 - Alpha
Classifier: License :: OSI Approved :: MIT License
Classifier: Programming Language :: Python
Requires-Python: >=3.10
License-File: LICENSE
Requires-Dist: beautifulsoup4==4.10.0
Requires-Dist: nltk==3.6.6
Requires-Dist: odfpy==1.4.1
Requires-Dist: tabulate==0.8.9
Requires-Dist: tqdm==4.66.3
Requires-Dist: pdfminer.six==20200517
Provides-Extra: dev
Requires-Dist: pytest; extra == "dev"
Requires-Dist: pre-commit; extra == "dev"
Provides-Extra: lint
Requires-Dist: pylint==3.0.2; extra == "lint"
Requires-Dist: mypy==1.7.1; extra == "lint"
Requires-Dist: flake8==6.1.0; extra == "lint"
Requires-Dist: black==24.3.0; extra == "lint"
Requires-Dist: types-tabulate; extra == "lint"
